openai_async/__init__.py
openai_async/async_requests.py
openai_async/openai_client.py
openai_async/response.py
openai_async_client/__init__.py
openai_async_client/async_requests.py
openai_async_client/model.py
openai_async_client/openai.py
openai_async_client/openai_client.py
openai_async_client/reader.py
openai_async_client/response.py
rolebotics/__init__.py
rolebotics/async_requests.py
rolebotics/openai_client.py
rolebotics/response.py
tests/__init__.py
tests/comp.py
tests/local.py
tests/local_2.py
tests/test_create.py
tests/test_openai_client.py
tests/view_df.py
openai_async_client-0.2.4.dist-info/LICENSE
openai_async_client-0.2.4.dist-info/METADATA
openai_async_client-0.2.4.dist-info/WHEEL
openai_async_client-0.2.4.dist-info/top_level.txt
openai_async_client-0.2.4.dist-info/RECORD
