Metadata-Version: 2.1
Name: openai-async-client
Version: 0.2.4
Summary: OpenAI async API with client side timeout, retry with exponential backoff and connection reuse
Home-page: https://github.com/itaim/openai-async-client.git
Author: Itai Marks
Author-email: itai.marks@gmail.com
License: MIT
Platform: UNKNOWN
Classifier: Development Status :: 3 - Alpha
Classifier: Intended Audience :: Developers
Classifier: License :: OSI Approved :: MIT License
Classifier: Programming Language :: Python :: 3.7
Classifier: Programming Language :: Python :: 3.8
Classifier: Programming Language :: Python :: 3.9
Classifier: Programming Language :: Python :: 3.10
Requires-Python: >=3.7.16
Requires-Dist: pydantic (>=1.8)
Requires-Dist: httpx (>=0.21.2)
Requires-Dist: backoff (>=2.0.0)
Requires-Dist: pandas (>=1.3.5)
